charmy-0.1.7.data/scripts/charmy
charmy-0.1.7.dist-info/WHEEL
charmy-0.1.7.dist-info/metadata.json
charmy-0.1.7.dist-info/RECORD
charmy-0.1.7.dist-info/DESCRIPTION.rst
charmy-0.1.7.dist-info/top_level.txt
charmy-0.1.7.dist-info/METADATA
charmy/utils.py
charmy/test.py
charmy/base.py
charmy/constants.py
charmy/helpers.py
charmy/__init__.py
charmy/installers/__init__.py
charmy/installers/linux/installer.py
charmy/installers/linux/__init__.py
charmy/installers/linux/other/installer.py
charmy/installers/linux/other/__init__.py
charmy/installers/linux/ubuntu/installer.py
charmy/installers/linux/ubuntu/constants.py
charmy/installers/linux/ubuntu/__init__.py
charmy/var/.keep
charmy/bin/charmy
charmy/commands/installer.py
charmy/commands/__init__.py
