Metadata-Version: 2.0
Name: charmy
Version: 0.1.7
Summary: Automated PyCharm installer for Linux.
Home-page: https://github.com/barseghyanartur/charmy
Author: Artur Barseghyan
Author-email: artur.barseghyan@gmail.com
License: GPL 2.0/LGPL 2.1
Keywords: pycharm,installer
Platform: UNKNOWN
Classifier: Programming Language :: Python
Classifier: Programming Language :: Python :: 2.6
Classifier: Programming Language :: Python :: 2.7
Classifier: Programming Language :: Python :: 3
Classifier: Programming Language :: Python :: 3.2
Classifier: Programming Language :: Python :: 3.3
Classifier: Programming Language :: Python :: 3.4
Classifier: Intended Audience :: Developers
Classifier: Operating System :: OS Independent
Classifier: Development Status :: 3 - Alpha
Classifier: Environment :: Console
Classifier: Topic :: Software Development
Classifier: Topic :: Text Editors :: Integrated Development Environments (IDE)
Requires-Dist: requests (>=2.0)
Requires-Dist: argparse
Requires-Dist: Flask (>=0.10)
Requires-Dist: Flask-SQLAlchemy (>=2.0)
Requires-Dist: six (>=1.4)
